LICENSE
MANIFEST.in
README.md
setup.py
crawl_knife/__init__.py
crawl_knife.egg-info/PKG-INFO
crawl_knife.egg-info/SOURCES.txt
crawl_knife.egg-info/dependency_links.txt
crawl_knife.egg-info/requires.txt
crawl_knife.egg-info/top_level.txt
crawl_knife/browser/__init__.py
crawl_knife/browser/base.py
crawl_knife/browser/chrome.py
crawl_knife/browser/firefox.py
crawl_knife/browser/add_ons/buster_captcha_solver_for_humans-1.3.1-chrome.zip
crawl_knife/browser/add_ons/ipmjngkmngdcdpmgmiebdmfbkcecdndc-1.5.crx
crawl_knife/browser/add_ons/uBlock_Origin-1.42.4.crx
crawl_knife/browser/js/stealth.min.js
crawl_knife/captcha/__init__.py
crawl_knife/captcha/normal_captcha.py
crawl_knife/captcha/recaptcha.py
test/test_driver.py