Metadata-Version: 2.1
Name: crawl-knife
Version: 0.1.6
Summary: Python crawl tool
Home-page: https://github.com/lusi1990/crawl_knife
Author: Master
Author-email: lusi2114@gmail.com
Requires-Python: >=3.6,<4
License-File: LICENSE
